ImageColorPicker/ColorPicker.py
ImageColorPicker/__init__.py
ImageColorPicker-0.1.dist-info/METADATA
ImageColorPicker-0.1.dist-info/WHEEL
ImageColorPicker-0.1.dist-info/top_level.txt
ImageColorPicker-0.1.dist-info/RECORD
